heatmap_grammar/__init__.py
heatmap_grammar/annotations.py
heatmap_grammar/clustering.py
heatmap_grammar/constants.py
heatmap_grammar/dendrograms.py
heatmap_grammar/guides.py
heatmap_grammar/heatmap.py
heatmap_grammar/markdown.py
heatmap_grammar/plot.py
heatmap_grammar/r.py
heatmap_grammar/rpy2_helpers.py
heatmap_grammar/scales.py
heatmap_grammar/unit.py
heatmap_grammar/utils.py
heatmap_grammar-0.0.5.dist-info/LICENSE
heatmap_grammar-0.0.5.dist-info/METADATA
heatmap_grammar-0.0.5.dist-info/WHEEL
heatmap_grammar-0.0.5.dist-info/top_level.txt
heatmap_grammar-0.0.5.dist-info/RECORD
