Metadata-Version: 2.1
Name: heatmap-grammar
Version: 0.0.5
Summary: Python heatmap interface using intuitive grammar of graphics, implemented as an rpy2 wrapper around ComplexHeatmap package
Author: Michał Krassowski
License: MIT license
Project-URL: Bug Tracker, https://github.com/krassowski/rpy2-complex-heatmap-grammar/issues
Project-URL: Source Code, https://github.com/krassowski/rpy2-complex-heatmap-grammar
Requires-Python: >=3.9
License-File: LICENSE
Requires-Dist: rpy2 (>=3.4.5)
Requires-Dist: pandas (>=1.3.0)
Requires-Dist: numpy (>=1.20)
Requires-Dist: ipython (>=8)
